{
  "versions": [
    {
      "git-tree": "33fc4428740bec314ef8e587734a6b7f76ec2100",
      "version-semver": "1.1.0-beta.4678811",
      "port-version": 0
    },
    {
      "git-tree": "c3a9e9d32a671e2d00687a35c5623cc0a5c44bd8",
      "version-semver": "1.1.0-beta.3826333",
      "port-version": 1
    },
    {
      "git-tree": "fecdd4a669ec8b90da2dd2874bb96def3981f366",
      "version-semver": "1.1.0-beta.3826333",
      "port-version": 0
    },
    {
      "git-tree": "f34c27d5d2bbf9c1abeb5d4afb2b11a8aa396006",
      "version-semver": "1.1.0-beta.3825855",
      "port-version": 0
    },
    {
      "git-tree": "eddd53900a155e8888f97e1ec11b35086f08d874",
      "version-semver": "1.1.0-beta.3687928",
      "port-version": 0
    },
    {
      "git-tree": "2b7e2065cd5f162b8cd9a054fe35fd3d30b22314",
      "version-semver": "1.1.0-beta.3589593",
      "port-version": 0
    },
    {
      "git-tree": "5078cbdbee3939dc3aefac674f6a92a2113fc90b",
      "version-semver": "1.1.0-beta.3585132",
      "port-version": 0
    }
  ]
}
